{
  "appInfo" : {
    "build" : "212.5457.46",
    "buildDate" : "2021-10-12T13:22:56.813Z[UTC]",
    "productCode" : "IC",
    "generated" : "2022-12-07T04:45:08.3776094Z",
    "os" : "Windows 10 10.0",
    "runtime" : "JetBrains s.r.o. 11.0.12 11.0.12+7-b1504.40"
  },
  "runtimeInfo" : {
    "maxMemory" : 536870912,
    "numberOfProcessors" : 16,
    "maxNumberOfIndexingThreads" : 4,
    "maxSizeOfFileForIntelliSense" : 2560000,
    "maxSizeOfFileForContentLoading" : 20971520
  },
  "projectIndexingHistory" : {
    "projectName" : "untitled",
    "times" : {
      "indexingReason" : "On project open",
      "totalUpdatingTime" : 4110791000,
      "indexingTime" : 78706500,
      "contentLoadingTime" : 5095114,
      "scanFilesTime" : 3909851700,
      "pushPropertiesTime" : 9000000,
      "indexExtensionsTime" : 0,
      "updatingStart" : "2022-12-07T04:45:04.2577604Z",
      "updatingEnd" : "2022-12-07T04:45:08.3706086Z",
      "totalSuspendedTime" : 0,
      "wasInterrupted" : false
    },
    "fileCount" : {
      "numberOfFileProviders" : 10,
      "numberOfScannedFiles" : 43562,
      "numberOfFilesIndexedByInfrastructureExtensionsDuringScan" : 0,
      "numberOfFilesScheduledForIndexingAfterScan" : 1,
      "numberOfFilesIndexedByInfrastructureExtensionsDuringIndexingStage" : 0,
      "numberOfFilesIndexedWithLoadingContent" : 1
    },
    "totalStatsPerFileType" : [ {
      "fileType" : "textmate",
      "partOfTotalProcessingTime" : {
        "part" : 29972000,
        "total" : 29972000
      },
      "partOfTotalContentLoadingTime" : {
        "part" : 2691100,
        "total" : 2691100
      },
      "totalNumberOfFiles" : 1,
      "totalFilesSize" : 353,
      "indexingSpeed" : {
        "totalBytes" : 353,
        "totalTime" : 29972000
      },
      "biggestContributors" : [ {
        "providerName" : "Indexable set contributor 'com.intellij.javaee.ExternalResourcesRootsProvider@16cf4eb9' (non-project)",
        "numberOfFiles" : 1,
        "totalFilesSize" : 353,
        "partOfTotalProcessingTimeOfThisFileType" : {
          "part" : 29972000,
          "total" : 29972000
        }
      } ]
    } ],
    "totalStatsPerIndexer" : [ {
      "indexId" : "IdIndex",
      "partOfTotalIndexingTime" : {
        "part" : 8925100,
        "total" : 11354200
      },
      "totalNumberOfFiles" : 1,
      "totalNumberOfFilesIndexedByExtensions" : 0,
      "totalFilesSize" : 353,
      "indexingSpeed" : {
        "totalBytes" : 353,
        "totalTime" : 8925100
      },
      "snapshotInputMappingStats" : {
        "totalRequests" : 0,
        "totalMisses" : 0,
        "totalHits" : 0
      }
    }, {
      "indexId" : "Trigram.Index",
      "partOfTotalIndexingTime" : {
        "part" : 2410400,
        "total" : 11354200
      },
      "totalNumberOfFiles" : 1,
      "totalNumberOfFilesIndexedByExtensions" : 0,
      "totalFilesSize" : 353,
      "indexingSpeed" : {
        "totalBytes" : 353,
        "totalTime" : 2410400
      },
      "snapshotInputMappingStats" : {
        "totalRequests" : 0,
        "totalMisses" : 0,
        "totalHits" : 0
      }
    }, {
      "indexId" : "filetypes",
      "partOfTotalIndexingTime" : {
        "part" : 18700,
        "total" : 11354200
      },
      "totalNumberOfFiles" : 1,
      "totalNumberOfFilesIndexedByExtensions" : 0,
      "totalFilesSize" : 353,
      "indexingSpeed" : {
        "totalBytes" : 353,
        "totalTime" : 18700
      },
      "snapshotInputMappingStats" : {
        "totalRequests" : 0,
        "totalMisses" : 0,
        "totalHits" : 0
      }
    } ],
    "scanningStatistics" : [ {
      "providerName" : "JDK 19",
      "numberOfScannedFiles" : 41619,
      "numberOfSkippedFiles" : 0,
      "numberOfFilesForIndexing" : 0,
      "numberOfFilesFullyIndexedByInfrastructureExtensions" : 0,
      "scanningTime" : 1812616100,
      "timeProcessingUpToDateFiles" : 0,
      "timeUpdatingContentLessIndexes" : 64672900,
      "timeIndexingWithoutContent" : 0
    }, {
      "providerName" : "Module 'untitled'",
      "numberOfScannedFiles" : 512,
      "numberOfSkippedFiles" : 0,
      "numberOfFilesForIndexing" : 0,
      "numberOfFilesFullyIndexedByInfrastructureExtensions" : 0,
      "scanningTime" : 796793800,
      "timeProcessingUpToDateFiles" : 0,
      "timeUpdatingContentLessIndexes" : 1839400,
      "timeIndexingWithoutContent" : 0
    }, {
      "providerName" : "Library JUnit5.7.0",
      "numberOfScannedFiles" : 810,
      "numberOfSkippedFiles" : 0,
      "numberOfFilesForIndexing" : 0,
      "numberOfFilesFullyIndexedByInfrastructureExtensions" : 0,
      "scanningTime" : 646324800,
      "timeProcessingUpToDateFiles" : 0,
      "timeUpdatingContentLessIndexes" : 3612900,
      "timeIndexingWithoutContent" : 0
    }, {
      "providerName" : "Indexable set contributor 'com.intellij.javaee.ExternalResourcesRootsProvider@16cf4eb9' (non-project)",
      "numberOfScannedFiles" : 222,
      "numberOfSkippedFiles" : 4,
      "numberOfFilesForIndexing" : 1,
      "numberOfFilesFullyIndexedByInfrastructureExtensions" : 0,
      "scanningTime" : 600156000,
      "timeProcessingUpToDateFiles" : 0,
      "timeUpdatingContentLessIndexes" : 103937900,
      "timeIndexingWithoutContent" : 0
    }, {
      "providerName" : "Library JUnit4",
      "numberOfScannedFiles" : 399,
      "numberOfSkippedFiles" : 0,
      "numberOfFilesForIndexing" : 0,
      "numberOfFilesFullyIndexedByInfrastructureExtensions" : 0,
      "scanningTime" : 588893200,
      "timeProcessingUpToDateFiles" : 0,
      "timeUpdatingContentLessIndexes" : 5694000,
      "timeIndexingWithoutContent" : 0
    }, {
      "providerName" : "Indexable set contributor 'com.intellij.javaee.ExternalResourcesRootsProvider@16cf4eb9' (project)",
      "numberOfScannedFiles" : 0,
      "numberOfSkippedFiles" : 0,
      "numberOfFilesForIndexing" : 0,
      "numberOfFilesFullyIndexedByInfrastructureExtensions" : 0,
      "scanningTime" : 0,
      "timeProcessingUpToDateFiles" : 0,
      "timeUpdatingContentLessIndexes" : 0,
      "timeIndexingWithoutContent" : 0
    }, {
      "providerName" : "Indexable set contributor 'Kotlin Script dependencies' (non-project)",
      "numberOfScannedFiles" : 0,
      "numberOfSkippedFiles" : 0,
      "numberOfFilesForIndexing" : 0,
      "numberOfFilesFullyIndexedByInfrastructureExtensions" : 0,
      "scanningTime" : 0,
      "timeProcessingUpToDateFiles" : 0,
      "timeUpdatingContentLessIndexes" : 0,
      "timeIndexingWithoutContent" : 0
    }, {
      "providerName" : "Indexable set contributor 'Scratches & Consoles' (project)",
      "numberOfScannedFiles" : 0,
      "numberOfSkippedFiles" : 0,
      "numberOfFilesForIndexing" : 0,
      "numberOfFilesFullyIndexedByInfrastructureExtensions" : 0,
      "scanningTime" : 0,
      "timeProcessingUpToDateFiles" : 0,
      "timeUpdatingContentLessIndexes" : 0,
      "timeIndexingWithoutContent" : 0
    }, {
      "providerName" : "Indexable set contributor 'Kotlin Script dependencies' (project)",
      "numberOfScannedFiles" : 0,
      "numberOfSkippedFiles" : 0,
      "numberOfFilesForIndexing" : 0,
      "numberOfFilesFullyIndexedByInfrastructureExtensions" : 0,
      "scanningTime" : 0,
      "timeProcessingUpToDateFiles" : 0,
      "timeUpdatingContentLessIndexes" : 0,
      "timeIndexingWithoutContent" : 0
    }, {
      "providerName" : "Indexable set contributor 'Scratches & Consoles' (non-project)",
      "numberOfScannedFiles" : 0,
      "numberOfSkippedFiles" : 0,
      "numberOfFilesForIndexing" : 0,
      "numberOfFilesFullyIndexedByInfrastructureExtensions" : 0,
      "scanningTime" : 0,
      "timeProcessingUpToDateFiles" : 0,
      "timeUpdatingContentLessIndexes" : 0,
      "timeIndexingWithoutContent" : 0
    } ],
    "fileProviderStatistics" : [ {
      "providerName" : "Indexable set contributor 'com.intellij.javaee.ExternalResourcesRootsProvider@16cf4eb9' (non-project)",
      "totalNumberOfIndexedFiles" : 1,
      "totalNumberOfFilesFullyIndexedByExtensions" : 0,
      "totalIndexingTime" : 56746600,
      "contentLoadingTime" : 5095114,
      "numberOfTooLargeForIndexingFiles" : 0,
      "slowIndexedFiles" : [ ]
    } ]
  }
}